connector/__init__.py
connector/api.py
insomnyak_connector/__init__.py
insomnyak_connector/api.py
utils/__init__.py
utils/utils.py
insomnyak_connector-0.0.103.dist-info/LICENSE
insomnyak_connector-0.0.103.dist-info/METADATA
insomnyak_connector-0.0.103.dist-info/WHEEL
insomnyak_connector-0.0.103.dist-info/top_level.txt
insomnyak_connector-0.0.103.dist-info/RECORD
